protobackend/__init__.py
protobackend/dispatcher.py
protobackend/exercise.py
protobackend/output.py
protobackend/payload.py
protobackend-0.1.0.dist-info/DESCRIPTION.rst
protobackend-0.1.0.dist-info/METADATA
protobackend-0.1.0.dist-info/RECORD
protobackend-0.1.0.dist-info/WHEEL
protobackend-0.1.0.dist-info/metadata.json
protobackend-0.1.0.dist-info/top_level.txt
