Metadata-Version: 2.0
Name: protobackend
Version: 0.1.0
Summary: Generic backend
Home-page: https://github.com/datacamp/protobackend
Author: Michael Chow
Author-email: michael@datacamp.com
License: UNKNOWN
Platform: UNKNOWN
